odoo10_addon_portal_sale_personal_data_only-10.0.1.0.2-py3.8-nspkg.pth
odoo/addons/portal_sale_personal_data_only/README.rst
odoo/addons/portal_sale_personal_data_only/__init__.py
odoo/addons/portal_sale_personal_data_only/__manifest__.py
odoo/addons/portal_sale_personal_data_only/hooks.py
odoo/addons/portal_sale_personal_data_only/data/portal_sale_security.xml
odoo/addons/portal_sale_personal_data_only/i18n/ca.po
odoo/addons/portal_sale_personal_data_only/i18n/es.po
odoo/addons/portal_sale_personal_data_only/i18n/portal_sale_personal_data_only.pot
odoo/addons/portal_sale_personal_data_only/readme/CONTRIBUTORS.rst
odoo/addons/portal_sale_personal_data_only/readme/DESCRIPTION.rst
odoo/addons/portal_sale_personal_data_only/readme/USAGE.rst
odoo/addons/portal_sale_personal_data_only/static/description/icon.png
odoo/addons/portal_sale_personal_data_only/static/description/index.html
odoo10_addon_portal_sale_personal_data_only-10.0.1.0.2.dist-info/METADATA
odoo10_addon_portal_sale_personal_data_only-10.0.1.0.2.dist-info/WHEEL
odoo10_addon_portal_sale_personal_data_only-10.0.1.0.2.dist-info/namespace_packages.txt
odoo10_addon_portal_sale_personal_data_only-10.0.1.0.2.dist-info/top_level.txt
odoo10_addon_portal_sale_personal_data_only-10.0.1.0.2.dist-info/RECORD
